mimicri/__init__.py
mimicri/_version.py
mimicri/example.py
mimicri/utils.py
mimicri/widget.py
mimicri/labextension/package.json
mimicri/labextension/static/122.0f949078d4622722866c.js
mimicri/labextension/static/158.fc4b197a3383b0c83fc3.js
mimicri/labextension/static/171.928ab9ed6007d460e598.js
mimicri/labextension/static/212.cc790cb576dd7db0fe2e.js
mimicri/labextension/static/212.cc790cb576dd7db0fe2e.js.LICENSE.txt
mimicri/labextension/static/261.ce45dd875c920319ec5e.js
mimicri/labextension/static/282.4a798a865e1a16e1a2dd.js
mimicri/labextension/static/335.f12f3df7dfd2075c38b5.js
mimicri/labextension/static/335.f12f3df7dfd2075c38b5.js.LICENSE.txt
mimicri/labextension/static/378.89bf9a088ae0539aa317.js
mimicri/labextension/static/470.48da2f77c12d398d6a35.js
mimicri/labextension/static/470.48da2f77c12d398d6a35.js.LICENSE.txt
mimicri/labextension/static/659.105afd1c9adf48ad89a6.js
mimicri/labextension/static/761.c2db9045bbadf0557880.js
mimicri/labextension/static/761.c2db9045bbadf0557880.js.LICENSE.txt
mimicri/labextension/static/846.b7623a232a6ee764ce2a.js
mimicri/labextension/static/890.e6a6a139fa78e9d4e708.js
mimicri/labextension/static/remoteEntry.6243434dfdfae17b833d.js
mimicri/labextension/static/style.js
mimicri/labextension/static/third-party-licenses.json
mimicri/nbextension/extension.js
mimicri/nbextension/index.js
mimicri/nbextension/index.js.LICENSE.txt
mimicri-0.1.0a0.data/data/etc/jupyter/nbconfig/notebook.d/mimicri.json
mimicri-0.1.0a0.data/data/share/jupyter/labextensions/mimicri/install.json
mimicri-0.1.0a0.data/data/share/jupyter/labextensions/mimicri/package.json
mimicri-0.1.0a0.data/data/share/jupyter/labextensions/mimicri/static/122.0f949078d4622722866c.js
mimicri-0.1.0a0.data/data/share/jupyter/labextensions/mimicri/static/158.fc4b197a3383b0c83fc3.js
mimicri-0.1.0a0.data/data/share/jupyter/labextensions/mimicri/static/171.928ab9ed6007d460e598.js
mimicri-0.1.0a0.data/data/share/jupyter/labextensions/mimicri/static/212.cc790cb576dd7db0fe2e.js
mimicri-0.1.0a0.dist-info/METADATA
mimicri-0.1.0a0.dist-info/WHEEL
mimicri-0.1.0a0.dist-info/top_level.txt
mimicri-0.1.0a0.dist-info/RECORD
